kangroll/__init__.py
kangroll/core.py
tests/__init__.py
tests/test_core.py
KANGROLL-0.1.13.dist-info/LICENSE
KANGROLL-0.1.13.dist-info/METADATA
KANGROLL-0.1.13.dist-info/WHEEL
KANGROLL-0.1.13.dist-info/top_level.txt
KANGROLL-0.1.13.dist-info/RECORD
