Metadata-Version: 2.1
Name: KANGROLL
Version: 0.1.13
Summary: KANGROLL to buid a bridge between science and nature
Home-page: https://github.com/williampolicy/kangroll
Author: Xiaowen Kang
Author-email: kangxiaowen@Gmail.com
Classifier: Programming Language :: Python :: 3
Classifier: License :: OSI Approved :: MIT License
Classifier: Operating System :: OS Independent
Requires-Python: >=3.6
License-File: LICENSE
